OnvifClient/__init__.py
eyecu_ipc_utils-0.1.0.dist-info/WHEEL
eyecu_ipc_utils-0.1.0.dist-info/METADATA
eyecu_ipc_utils-0.1.0.dist-info/RECORD
