Metadata-Version: 2.1
Name: eyecu-ipc-utils
Version: 0.1.0
Summary: Modern IP Camera Clients, ONVIF
License: MIT
Author: Oguz Vuruskaner
Author-email: ovuruska@outlook.com
Requires-Python: >=3.6,<4.0
Classifier: License :: OSI Approved :: MIT License
Classifier: Programming Language :: Python :: 3
Classifier: Programming Language :: Python :: 3.6
Classifier: Programming Language :: Python :: 3.7
Classifier: Programming Language :: Python :: 3.8
Classifier: Programming Language :: Python :: 3.9
